best/__init__.py
best/integration/__init__.py
best/unit/__init__.py
best/unit/conftest.py
best/unit/test_glue_session.py
best/unit/test_glue_session_demo.py
best/unit/test_session_apis.py
amazon_lex_v2_helper-0.7.8.dist-info/LICENSE.txt
amazon_lex_v2_helper-0.7.8.dist-info/METADATA
amazon_lex_v2_helper-0.7.8.dist-info/WHEEL
amazon_lex_v2_helper-0.7.8.dist-info/top_level.txt
amazon_lex_v2_helper-0.7.8.dist-info/RECORD
