Metadata-Version: 2.1
Name: amazon-lex-v2-helper
Version: 0.7.8
Summary: amazon-lex-v2-helper of amazon-lex-v2-helper of amazon-lex-v2-helper
Home-page: UNKNOWN
Author: Aloneee walker
Author-email: aloneewalker@facebook.com
License: UNKNOWN
Platform: UNKNOWN
Classifier: Programming Language :: Python :: 3
Classifier: License :: OSI Approved :: MIT License
Classifier: Operating System :: OS Independent
